multi_tenant/__init__.py
multi_tenant/admin.py
multi_tenant/apps.py
multi_tenant/constants.py
multi_tenant/middleware.py
multi_tenant/models.py
multi_tenant/routers.py
multi_tenant/signals.py
multi_tenant/storage.py
multi_tenant/utils.py
multi_tenant/management/__init__.py
multi_tenant/management/commands/__init__.py
multi_tenant/management/commands/migrate.py
multi_tenant/management/commands/migrate_schemas.py
multi_tenant/migration_executors/__init__.py
multi_tenant/migration_executors/base.py
multi_tenant/migration_executors/parallel.py
multi_tenant/migration_executors/standard.py
multi_tenant/postgresql_backend/__init__.py
multi_tenant/postgresql_backend/base.py
multi_tenant/postgresql_backend/introspection.py
multi_tenant/test/__init__.py
multi_tenant/test/client.py
django_multi_tenants-0.1.3.3.dist-info/LICENSE
django_multi_tenants-0.1.3.3.dist-info/METADATA
django_multi_tenants-0.1.3.3.dist-info/WHEEL
django_multi_tenants-0.1.3.3.dist-info/top_level.txt
django_multi_tenants-0.1.3.3.dist-info/RECORD
