Metadata-Version: 2.1
Name: django-multi-tenants
Version: 0.1.3.3
Summary: Multi tenant support for Django using PostgreSQL schemas.
Home-page: https://gitlab.com/crstnrm/django-multi-tenants
Author: Cristian Restrepo
Author-email: crstnrrm@gmail.com
License: MIT
Platform: UNKNOWN
Classifier: License :: OSI Approved :: MIT License
Classifier: Framework :: Django
Classifier: Framework :: Django :: 2.2
Classifier: Framework :: Django :: 3.0
Classifier: Framework :: Django :: 3.1
Classifier: Framework :: Django :: 3.2
Classifier: Programming Language :: Python
Classifier: Programming Language :: Python :: 3.6
Classifier: Programming Language :: Python :: 3.7
Classifier: Programming Language :: Python :: 3.8
Classifier: Topic :: Database
Classifier: Topic :: Software Development :: Libraries
Requires-Python: >=3.6
License-File: LICENSE
Requires-Dist: Django >=2.2.0
Requires-Dist: django-tenant-schemas
